everinfer/__init__.py
everinfer/client.py
everinfer/engine.py
everinfer/messages.py
everinfer/proto/Error.py
everinfer/proto/ErrorType.py
everinfer/proto/FindSource.py
everinfer/proto/Identity.py
everinfer/proto/Image.py
everinfer/proto/JoinSource.py
everinfer/proto/KVData.py
everinfer/proto/LinkLog.py
everinfer/proto/Message.py
everinfer/proto/NodeAccept.py
everinfer/proto/NodeAlive.py
everinfer/proto/NodeJoined.py
everinfer/proto/Payload.py
everinfer/proto/Pipeline.py
everinfer/proto/PipelineList.py
everinfer/proto/ProfileSpec.py
everinfer/proto/RawData.py
everinfer/proto/SourceAlive.py
everinfer/proto/Status.py
everinfer/proto/Task.py
everinfer/proto/Tensor.py
everinfer/proto/TensorType.py
everinfer/proto/__init__.py
everinfer-0.1.8.dist-info/LICENSE
everinfer-0.1.8.dist-info/METADATA
everinfer-0.1.8.dist-info/WHEEL
everinfer-0.1.8.dist-info/top_level.txt
everinfer-0.1.8.dist-info/RECORD
