Metadata-Version: 2.1
Name: everinfer
Version: 0.1.8
Summary: Everinfer client to run scalable distributed ML inference with low latency.
Home-page: https://github.com/everinfer/everinfer
Author: Everinfer
Author-email: hello@everinfer.ai
License: MIT license
Keywords: everinfer
Classifier: Development Status :: 2 - Pre-Alpha
Classifier: Intended Audience :: Developers
Classifier: License :: OSI Approved :: MIT License
Classifier: Natural Language :: English
Classifier: Programming Language :: Python :: 3
Classifier: Programming Language :: Python :: 3.6
Classifier: Programming Language :: Python :: 3.7
Classifier: Programming Language :: Python :: 3.8
Requires-Python: >=3.6
License-File: LICENSE
Requires-Dist: numpy
Requires-Dist: flatbuffers (==2.0)
Requires-Dist: eclipse-zenoh (==0.7.2rc0)
Requires-Dist: Pillow
